{"randomArticles":[{"articleTitle":"Solo | 优雅的使用 Solo 静态博客","articleAbstractText":"这篇文章只针对部署静态博客的小伙伴，提供一些想法和思路。","articleStatus":0,"articlePermalink":"/articles/2020/06/01/1591015397541.html","articleImg1URL":"https://b3logfile.com/bing/20180517.jpg?imageView2/1/w/960/h/540/interlace/1/q/100"},{"articleTitle":"日志 | 兵荒马乱的八月","articleAbstractText":"工作只是生活的一部分 这个月一直在连轴转，微纳研究所的检测仪项目摄像头一直有问题，华为 P30 摄像头录制 4K 视频吊起摄像头就卡住，小老鼠研究的头发都白了，周五拿来了他们的 P30 测试机，说来项目方确实大方。 因为腿腿的关系认识了饭哥，接到了一个 OA 的项目，饭哥公司的那个项目经理一直在催进度，仅仅是合作关系而非上下级关系，合同也签到 10 月中旬签完没一周就开始催，很想回怼，碍于情面，私下密了饭哥说信不过就把钱退了找别人吧。 都是打工的，何必表现的高人一等，合着我做个外包您还当我是您公司员工一样压榨？ 公司 SRM（供应商关系管理系统）一直在做供应商这块的业务，加班已经是家常便饭，常常有负面情绪，会把自己的薪资和股票收益、外包收益去做对比，常常会觉得不值，是真的不值。资本社会是真的只有剥削。 一直在考虑第二条路，工作不等于上班，也不该这么压抑，外包和基金都是我作出的尝试，高强度的工作确实会让人麻木，上班下班，没时间看书、思考、尝试。 私下和 Wood 吃了顿饭，聊了下 GSP 系统的开发，40 多岁的老项目经理胡诌诌，喝喝啤酒脸也红了。我好多比我年长的朋友，小老鼠 30 多，....","articleStatus":0,"articlePermalink":"/articles/2020/08/29/1598633703417.html","articleImg1URL":"https://b3logfile.com/bing/20200310.jpg?imageView2/1/w/960/h/540/interlace/1/q/100"},{"articleTitle":"书单 | 花开花落，云舒云卷","articleAbstractText":"感谢每一位给我们带来好故事的作者。","articleStatus":0,"articlePermalink":"/books.html","articleImg1URL":"https://b3logfile.com/bing/20200513.jpg?imageView2/1/w/1280/h/720/interlace/1/q/100"},{"articleTitle":" 日志 | 毕业一周年","articleAbstractText":"今天小甲发了一篇公众号推文，标题就是毕业一周年，才知道他跟我一样都是去年毕业的小伙儿。截止我写这篇文章已经有 1w4+的阅读，如果按照公众号推文打开率 5%来算的话，他已经有 28w+粉丝了，一方面觉得他真的很厉害，另一方面觉得这是他努力应得的。","articleStatus":0,"articlePermalink":"/articles/2018/10/19/1539958579000.html","articleImg1URL":"https://b3logfile.com/bing/20190614.jpg?imageView2/1/w/1280/h/720/interlace/1/q/100"}]}